mautrix_twitter/__init__.py
mautrix_twitter/__main__.py
mautrix_twitter/backfill.py
mautrix_twitter/config.py
mautrix_twitter/example-config.yaml
mautrix_twitter/formatter.py
mautrix_twitter/get_version.py
mautrix_twitter/matrix.py
mautrix_twitter/portal.py
mautrix_twitter/puppet.py
mautrix_twitter/user.py
mautrix_twitter/version.py
mautrix_twitter/commands/__init__.py
mautrix_twitter/commands/auth.py
mautrix_twitter/commands/conn.py
mautrix_twitter/commands/typehint.py
mautrix_twitter/db/__init__.py
mautrix_twitter/db/backfill.py
mautrix_twitter/db/message.py
mautrix_twitter/db/portal.py
mautrix_twitter/db/puppet.py
mautrix_twitter/db/reaction.py
mautrix_twitter/db/upgrade.py
mautrix_twitter/db/user.py
mautrix_twitter/util/__init__.py
mautrix_twitter/util/color_log.py
mautrix_twitter/web/__init__.py
mautrix_twitter/web/provisioning_api.py
mautrix_twitter-0.1.8.data/data/example-config.yaml
mautwitdm/__init__.py
mautwitdm/conversation.py
mautwitdm/dispatcher.py
mautwitdm/errors.py
mautwitdm/poller.py
mautwitdm/streamer.py
mautwitdm/twitter.py
mautwitdm/uploader.py
mautwitdm/types/__init__.py
mautwitdm/types/conversation.py
mautwitdm/types/entry.py
mautwitdm/types/message.py
mautwitdm/types/message_attachment.py
mautwitdm/types/message_entity.py
mautwitdm/types/reaction.py
mautwitdm/types/response.py
mautwitdm/types/stream_payload.py
mautwitdm/types/user.py
mautwitdm/types/util.py
mautrix_twitter-0.1.8.dist-info/LICENSE
mautrix_twitter-0.1.8.dist-info/METADATA
mautrix_twitter-0.1.8.dist-info/WHEEL
mautrix_twitter-0.1.8.dist-info/top_level.txt
mautrix_twitter-0.1.8.dist-info/RECORD
